realpid/__init__.py
realpid/py.typed
realpid/realpid.py
realpid/realpid.pyi
realpid-0.0.1.dist-info/LICENSE.md
realpid-0.0.1.dist-info/METADATA
realpid-0.0.1.dist-info/WHEEL
realpid-0.0.1.dist-info/top_level.txt
realpid-0.0.1.dist-info/RECORD
