Metadata-Version: 2.1
Name: realpid
Version: 0.0.1
Summary: A real PID
Home-page: https://github.com/chentyra/RealPID
Author: Federica Oliva
Keywords: pid,PID,control,controller,real
Classifier: Programming Language :: Python :: 3
Classifier: License :: OSI Approved :: MIT License
Classifier: Operating System :: OS Independent
Requires-Python: >=3.7
License-File: LICENSE.md
